{
    "doi": "10.1007/s10551-021-04817-0",
    "title": "How to Deter Financial Misconduct if Crime Pays?",
    "authors": [
        "Karol Marek Klimczak",
        "Alejo José G. Sisón",
        "María Lena Mateu Prats",
        "Maximilian B. Torres"
    ],
    "abstract": "Abstract Financial misconduct has come into the spotlight in recent years, causing market regulators to increase the reach and severity of interventions. We show that at times the economic benefits of illicit financial activity outweigh the costs of litigation. We illustrate our argument with data from the US Securities and Exchanges Commission and a case of investment misconduct. From the neoclassical economic paradigm, which follows utilitarian thinking, it is rational to engage in misconduct. Still, the majority of professionals refrain from misconduct, foregoing economic rewards. We suggest financial activity could be reimagined taking into account intrinsic and prosocial motivations. A virtue ethics framework could also be applied, linking financial behavior to the quest for moral excellence and shared flourishing. By going beyond utilitarian thinking and considering alternative models, we offer a fuller account of financial behavior and a better perspective from which to design deterrence methods.",
    "issued": "2022",
    "type": "article",
    "subject": [
        "Economics",
        "Law and economics",
        "Finance",
        "Business",
        "Public relations",
        "Political science",
        "Social psychology",
        "Law",
        "Psychology",
        "Biochemistry",
        "Chemistry"
    ],
    "language": "en",
    "uri": "https://link.springer.com/content/pdf/10.1007/s10551-021-04817-0.pdf",
    "rights.uri": "cc-by",
    "_local.pdf_path": "pdf_openalex\\10.1007_s10551-021-04817-0.pdf"
}