{
    "doi": "10.4312/dp.46.6",
    "title": "The beginning of the Neolithic on the Upper Volga (Russia)",
    "authors": [
        "Nataliya A. Tsvetkova"
    ],
    "abstract": "The appearance of the Neolithic in the Upper Volga region is to be associated with infiltrations of notch-ware pottery-makers into the indigenous Mesolithic populations. Most likely the first vessels were imported into the region as final goods. The undistinguished differences between the Final Mesolithic and the Early Neolithic stone industries prove that this invasion was not a largescale one. This episode should be regarded as transitional from the Mesolithic to the Neolithic (i.e., as part of the process of Neolithisation). The non-ornamented/notch-ware ceramics tradition first established in the local cultural environment was soon after discontinued by the appearance of the populations with multi-compound comb-ware pottery about 6500-6400 uncal BP.",
    "issued": "2019",
    "type": "article",
    "subject": [
        "Mesolithic",
        "Pottery",
        "Archaeology",
        "Volga region",
        "Geography",
        "Ancient history",
        "Indigenous",
        "History",
        "Biology",
        "Ecology"
    ],
    "language": "en",
    "uri": "https://revije.ff.uni-lj.si/DocumentaPraehistorica/article/download/46.6/8734",
    "rights.uri": "cc-by-sa",
    "_local.pdf_path": "pdf_openalex/10.4312_dp.46.6.pdf"
}